README.rst
setup.py
better_bencode/__init__.py
better_bencode/__main__.py
better_bencode/_fast.c
better_bencode/_pure.py
better_bencode.egg-info/PKG-INFO
better_bencode.egg-info/SOURCES.txt
better_bencode.egg-info/dependency_links.txt
better_bencode.egg-info/top_level.txt